{
    "basics": {
      "name": "Ezequiel Arce",
      "label": "Full Stack Developer con más de 2 años de experiencia",
      "image": "/Fotocv.jpg",
      "email": "ezequiel.arce.8296@gmail.com",
      "phone": "221-4180252",
      "url": "https://",
      "summary": "+2 año de experiencia como Desarrollador Web. Actualmente soy programador freelance. Vivo en la ciudad de La plata, provincia de Buenos Aires - Argentina.",
      "location": {
        "address": "",
        "postalCode": "1900",
        "city": "La Plata",
        "countryCode": "AR",
        "region": "Argentina"
      },
      "profiles": [
        {
          "network": "LinkedIn",
          "username": "ezearce",
          "url": "https://www.linkedin.com/in/ezearce/"
        },
      {
        "network": "GitHub",
        "username": "EzeArc",
        "url": "https://github.com/EzeArc"
      }
    ]
    },
    "work": [{
      "name": "Podología Gonnet - LP",
      "position": "Desarrollador Frontend",
      "url": "https://podogonnet.netlify.app/",
      "startDate": "2024-04-10",
      "endDate": null,
      "summary": "Crecación de la aplicación web para el centro de podología. Diseño de UI accesible para todos los usuario. Implementación de sistema de calendario con reserva de turnos para los pacientes. Configuración del entorno de desarrollo y producción mediante Github Actions y Netlify.",
      "highlights": [
        "Started the company"
      ]
    },
    {
      "name": "Sannar ONG",
      "position": "Desarrollador Frontend",
      "url": "https://sannar.makitech.com.ar/",
      "startDate": "2024-05-01",
      "endDate": null,
      "summary": "Lideré el diseño y desarrollo de la aplicación web para Sannar ONG. Los usuarios puedan acceder mediante la web a la información, noticias y artículos que la ong brinda. Además de poder contactar y consultar de manera online a la ONG. Fomenté buenas prácticas y mejoras en la cultura de rendimiento, además de la entrega rápida de valor a los usuarios.",
      "highlights": [
        "Started the company"
      ]
    }
    ],
    "volunteer": [{
      "organization": "Organization",
      "position": "Volunteer",
      "url": "https://organization.com/",
      "startDate": "2012-01-01",
      "endDate": "2013-01-01",
      "summary": "Description…",
      "highlights": [
        "Awarded 'Volunteer of the Month'"
      ]
    }],
    "education": [{
      "institution": "Universitat Oberta de Catalunya",
      "url": "https://www.uoc.edu/portal/es/index.html",
      "area": "Ingeniero de Software",
      "studyType": "Bachelor",
      "startDate": "2003-01-01",
      "endDate": "2009-01-01",
      "score": "4.0",
      "courses": [
        "DB1101 - Basic SQL"
      ]
    }],
    "awards": [{
      "title": "Award",
      "date": "2014-11-01",
      "awarder": "Company",
      "summary": "There is no spoon."
    }],
    "certificates": [{
      "name": "Certificate",
      "date": "2021-11-07",
      "issuer": "Company",
      "url": "https://certificate.com"
    }],
    "publications": [{
      "name": "Publication",
      "publisher": "Company",
      "releaseDate": "2014-10-01",
      "url": "https://publication.com",
      "summary": "Description…"
    }],
    "skills": [
        {
          "name": "HTML",
          "level": "Master",
          "keywords": [
            "Desarrollo Web", "Frontend"
          ]
        },
        {
          "name": "CSS",
          "level": "Master",
          "keywords": [
            "Desarrollo Web", "Frontend", "Diseño Responsive"
          ]
        },
        {
          "name": "JavaScript",
          "level": "Master",
          "keywords": [
            "Desarrollo Web", "Frontend", "Backend", "Fullstack"
          ]
        },
        {
          "name": "Tailwind",
          "level": "Avanzado",
          "keywords": [
            "Desarrollo Web", "Frontend", "CSS Framework", "Diseño Responsive"
          ]
        },
        {
          "name": "TypeScript",
          "level": "Avanzado",
          "keywords": [
            "Desarrollo Web", "Frontend", "Backend", "JavaScript Superset"
          ]
        },
        {
          "name": "Node",
          "level": "Avanzado",
          "keywords": [
            "Desarrollo Web", "Backend", "JavaScript", "Servidor"
          ]
        },
        {
          "name": "MySQL",
          "level": "Avanzado",
          "keywords": [
            "Bases de Datos", "SQL", "Almacenamiento de Datos", "Backend"
          ]
        },
        {
          "name": "Git",
          "level": "Avanzado",
          "keywords": [
            "Control de Versiones", "Colaboración", "Código Fuente"
          ]
        },
        {
          "name": "GitHub",
          "level": "Avanzado",
          "keywords": [
            "Control de Versiones", "Colaboración", "Código Fuente", "Git"
          ]
        },
        {
          "name": "Angular",
          "level": "Avanzado",
          "keywords": [
            "Desarrollo Web", "Frontend", "Angular Framework", "Angular Material", "Angular Animations"
          ]
        },
        {
          "name": "React",
          "level": "Avanzado",
          "keywords": [
            "Desarrollo Web", "Frontend", "JavaScript Library", "UI"
          ]
        },{
          "name": "Java",
          "level": "Avanzado",
          "keywords": [
            "Desarrollo de API", "Backend", "POO", "JPA"
          ]
        },{
          "name": "Spring Boot",
          "level": "Avanzado",
          "keywords": [
            "Desarrollo de API", "Backend", "Spring Security", "Bases de Datos", "JPA"
          ]
        }
      ],
    "languages": [{
      "language": "Spanish",
      "fluency": "Native speaker"
    }, {
      "language": "English",
      "fluency": "Intermidiate"
    }],
    "interests": [{
      "name": "Wildlife",
      "keywords": [
        "Ferrets",
        "Unicorns"
      ]
    }],
    "references": [{
      "name": "Jane Doe",
      "reference": "Reference…"
    }],
    "projects": [
      {
      "name": "Sannar ONG",
      "isActive": true,
      "description": "Página web del centro de investigación del Cannabis Medicinal Sannar ONG",
      "highlights": [
        "Cannabis Medicinal",
        "Bienestar natural"
      ],
      "url": "https://sannar.makitech.com.ar/"
    }, {
      "name": "PodoGonnet",
      "isActive": true,
      "description": "Página web del centro de podología PodoGonnet - Lp",
      "highlights": [
        "Reservas de turnos",
        "Agenda y horarios",
        "Cuidado personal"
      ],
      "url": "https://podogonnet.netlify.app/"
    }]
  }